ignite/__init__.py
ignite/cli.py
ignite/client.py
ignite/config.py
ignite/auth/__init__.py
ignite/commands/__init__.py
ignite/commands/add.py
ignite/commands/create.py
ignite/commands/delete.py
ignite/commands/get.py
ignite/commands/list.py
ignite/commands/reissue.py
ignite/commands/set.py
ignite/commands/update.py
ignite/models/__init__.py
ignite/utils/__init__.py
ignite/utils/output.py
igniteops_sdk/__init__.py
igniteops_sdk/client.py
igniteops_sdk/errors.py
igniteops_sdk/types.py
igniteops_sdk/api/__init__.py
igniteops_sdk/api/api_keys/__init__.py
igniteops_sdk/api/api_keys/create_key.py
igniteops_sdk/api/api_keys/list_keys.py
igniteops_sdk/api/api_keys/reissue_key.py
igniteops_sdk/api/api_keys/revoke_key.py
igniteops_sdk/api/integrations/__init__.py
igniteops_sdk/api/integrations/create_cloud_integration.py
igniteops_sdk/api/integrations/create_repository.py
igniteops_sdk/api/integrations/delete_cloud_integration.py
igniteops_sdk/api/integrations/delete_repository.py
igniteops_sdk/api/integrations/get_cloud_integration.py
igniteops_sdk/api/integrations/get_cloud_integrations.py
igniteops_sdk/api/integrations/get_repositories.py
igniteops_sdk/api/integrations/update_cloud_integration.py
igniteops_sdk/api/project_team/__init__.py
igniteops_sdk/api/project_team/get_v1_users.py
igniteops_sdk/api/projects/__init__.py
igniteops_sdk/api/projects/add_project_team_member.py
igniteops_sdk/api/projects/create_project.py
igniteops_sdk/api/projects/create_project_release.py
igniteops_sdk/api/projects/delete_project.py
igniteops_sdk/api/projects/get_project.py
igniteops_sdk/api/projects/get_project_activity.py
igniteops_sdk/api/projects/get_project_releases.py
igniteops_sdk/api/projects/get_project_team.py
igniteops_sdk/api/projects/get_projects.py
igniteops_sdk/api/projects/remove_project_team_member.py
igniteops_sdk/api/projects/set_project_favourite.py
igniteops_sdk/api/projects/update_project_release.py
igniteops_sdk/api/projects/update_project_team_member.py
ignite_cli-0.2.1.dist-info/METADATA
ignite_cli-0.2.1.dist-info/WHEEL
ignite_cli-0.2.1.dist-info/entry_points.txt
ignite_cli-0.2.1.dist-info/top_level.txt
ignite_cli-0.2.1.dist-info/RECORD
