Metadata-Version: 2.4
Name: ignite-cli
Version: 0.2.1
Summary: IgniteOps Command-Line Interface
Author-email: IgniteOps <support@igniteops.io>
License: MIT
Requires-Python: >=3.8
Requires-Dist: typer[all]>=0.9.0
Requires-Dist: requests>=2.31.0
Requires-Dist: rich>=13.0.0
Requires-Dist: pydantic>=2.0.0
Requires-Dist: httpx>=0.23.0
Requires-Dist: attrs>=22.0.0
Requires-Dist: python-dateutil>=2.8.0
Requires-Dist: PyYAML>=6.0
Requires-Dist: click>=8.0.0
Provides-Extra: dev
Requires-Dist: mkdocs>=1.5.0; extra == "dev"
Requires-Dist: mkdocs-material>=9.0.0; extra == "dev"
